{
  "1998年": [
    {
      "地區": "臺灣地區",
      "可支配所得": "873175"
    },
    {
      "地區": "新北市",
      "可支配所得": "875751"
    },
    {
      "地區": "臺北市",
      "可支配所得": "1196141"
    },
    {
      "地區": "桃園市",
      "可支配所得": "950235"
    },
    {
      "地區": "臺中市",
      "可支配所得": "891503"
    },
    {
      "地區": "臺南市",
      "可支配所得": "744397"
    },
    {
      "地區": "高雄市",
      "可支配所得": "831902"
    },
    {
      "地區": "宜蘭縣",
      "可支配所得": "783504"
    },
    {
      "地區": "新竹縣",
      "可支配所得": "910821"
    },
    {
      "地區": "苗栗縣",
      "可支配所得": "761381"
    },
    {
      "地區": "彰化縣",
      "可支配所得": "804131"
    },
    {
      "地區": "南投縣",
      "可支配所得": "725605"
    },
    {
      "地區": "雲林縣",
      "可支配所得": "661698"
    },
    {
      "地區": "嘉義縣",
      "可支配所得": "580982"
    },
    {
      "地區": "屏東縣",
      "可支配所得": "742449"
    },
    {
      "地區": "臺東縣",
      "可支配所得": "562213"
    },
    {
      "地區": "花蓮縣",
      "可支配所得": "718903"
    },
    {
      "地區": "澎湖縣",
      "可支配所得": "504624"
    },
    {
      "地區": "基隆市",
      "可支配所得": "804378"
    },
    {
      "地區": "新竹市",
      "可支配所得": "960109"
    },
    {
      "地區": "嘉義市",
      "可支配所得": "873466"
    }
  ],
  "1999年": [
    {
      "地區": "臺灣地區",
      "可支配所得": "889053"
    },
    {
      "地區": "新北市",
      "可支配所得": "892692"
    },
    {
      "地區": "臺北市",
      "可支配所得": "1208578"
    },
    {
      "地區": "桃園市",
      "可支配所得": "944302"
    },
    {
      "地區": "臺中市",
      "可支配所得": "925933"
    },
    {
      "地區": "臺南市",
      "可支配所得": "736363"
    },
    {
      "地區": "高雄市",
      "可支配所得": "846303"
    },
    {
      "地區": "宜蘭縣",
      "可支配所得": "826697"
    },
    {
      "地區": "新竹縣",
      "可支配所得": "968579"
    },
    {
      "地區": "苗栗縣",
      "可支配所得": "779814"
    },
    {
      "地區": "彰化縣",
      "可支配所得": "755213"
    },
    {
      "地區": "南投縣",
      "可支配所得": "858800"
    },
    {
      "地區": "雲林縣",
      "可支配所得": "742533"
    },
    {
      "地區": "嘉義縣",
      "可支配所得": "628540"
    },
    {
      "地區": "屏東縣",
      "可支配所得": "718919"
    },
    {
      "地區": "臺東縣",
      "可支配所得": "574406"
    },
    {
      "地區": "花蓮縣",
      "可支配所得": "711084"
    },
    {
      "地區": "澎湖縣",
      "可支配所得": "588607"
    },
    {
      "地區": "基隆市",
      "可支配所得": "868974"
    },
    {
      "地區": "新竹市",
      "可支配所得": "1011061"
    },
    {
      "地區": "嘉義市",
      "可支配所得": "796358"
    }
  ],
  "2000年": [
    {
      "地區": "臺灣地區",
      "可支配所得": "891445"
    },
    {
      "地區": "新北市",
      "可支配所得": "882634"
    },
    {
      "地區": "臺北市",
      "可支配所得": "1237777"
    },
    {
      "地區": "桃園市",
      "可支配所得": "985426"
    },
    {
      "地區": "臺中市",
      "可支配所得": "855399"
    },
    {
      "地區": "臺南市",
      "可支配所得": "763523"
    },
    {
      "地區": "高雄市",
      "可支配所得": "835452"
    },
    {
      "地區": "宜蘭縣",
      "可支配所得": "805088"
    },
    {
      "地區": "新竹縣",
      "可支配所得": "1021919"
    },
    {
      "地區": "苗栗縣",
      "可支配所得": "788159"
    },
    {
      "地區": "彰化縣",
      "可支配所得": "757817"
    },
    {
      "地區": "南投縣",
      "可支配所得": "729438"
    },
    {
      "地區": "雲林縣",
      "可支配所得": "694363"
    },
    {
      "地區": "嘉義縣",
      "可支配所得": "725986"
    },
    {
      "地區": "屏東縣",
      "可支配所得": "767107"
    },
    {
      "地區": "臺東縣",
      "可支配所得": "641298"
    },
    {
      "地區": "花蓮縣",
      "可支配所得": "741877"
    },
    {
      "地區": "澎湖縣",
      "可支配所得": "697315"
    },
    {
      "地區": "基隆市",
      "可支配所得": "863374"
    },
    {
      "地區": "新竹市",
      "可支配所得": "1099335"
    },
    {
      "地區": "嘉義市",
      "可支配所得": "808703"
    }
  ],
  "2001年": [
    {
      "地區": "臺灣地區",
      "可支配所得": "868651"
    },
    {
      "地區": "新北市",
      "可支配所得": "896186"
    },
    {
      "地區": "臺北市",
      "可支配所得": "1217932"
    },
    {
      "地區": "桃園市",
      "可支配所得": "923301"
    },
    {
      "地區": "臺中市",
      "可支配所得": "866609"
    },
    {
      "地區": "臺南市",
      "可支配所得": "717591"
    },
    {
      "地區": "高雄市",
      "可支配所得": "820781"
    },
    {
      "地區": "宜蘭縣",
      "可支配所得": "725890"
    },
    {
      "地區": "新竹縣",
      "可支配所得": "922675"
    },
    {
      "地區": "苗栗縣",
      "可支配所得": "777341"
    },
    {
      "地區": "彰化縣",
      "可支配所得": "706694"
    },
    {
      "地區": "南投縣",
      "可支配所得": "694028"
    },
    {
      "地區": "雲林縣",
      "可支配所得": "732284"
    },
    {
      "地區": "嘉義縣",
      "可支配所得": "660383"
    },
    {
      "地區": "屏東縣",
      "可支配所得": "679721"
    },
    {
      "地區": "臺東縣",
      "可支配所得": "627005"
    },
    {
      "地區": "花蓮縣",
      "可支配所得": "744651"
    },
    {
      "地區": "澎湖縣",
      "可支配所得": "595548"
    },
    {
      "地區": "基隆市",
      "可支配所得": "775698"
    },
    {
      "地區": "新竹市",
      "可支配所得": "1101828"
    },
    {
      "地區": "嘉義市",
      "可支配所得": "785582"
    }
  ],
  "2002年": [
    {
      "地區": "臺灣地區",
      "可支配所得": "875919"
    },
    {
      "地區": "新北市",
      "可支配所得": "899975"
    },
    {
      "地區": "臺北市",
      "可支配所得": "1232387"
    },
    {
      "地區": "桃園市",
      "可支配所得": "979979"
    },
    {
      "地區": "臺中市",
      "可支配所得": "843776"
    },
    {
      "地區": "臺南市",
      "可支配所得": "746442"
    },
    {
      "地區": "高雄市",
      "可支配所得": "801248"
    },
    {
      "地區": "宜蘭縣",
      "可支配所得": "695577"
    },
    {
      "地區": "新竹縣",
      "可支配所得": "949374"
    },
    {
      "地區": "苗栗縣",
      "可支配所得": "762664"
    },
    {
      "地區": "彰化縣",
      "可支配所得": "799305"
    },
    {
      "地區": "南投縣",
      "可支配所得": "683359"
    },
    {
      "地區": "雲林縣",
      "可支配所得": "688011"
    },
    {
      "地區": "嘉義縣",
      "可支配所得": "611036"
    },
    {
      "地區": "屏東縣",
      "可支配所得": "782085"
    },
    {
      "地區": "臺東縣",
      "可支配所得": "651312"
    },
    {
      "地區": "花蓮縣",
      "可支配所得": "689347"
    },
    {
      "地區": "澎湖縣",
      "可支配所得": "605641"
    },
    {
      "地區": "基隆市",
      "可支配所得": "722155"
    },
    {
      "地區": "新竹市",
      "可支配所得": "1027437"
    },
    {
      "地區": "嘉義市",
      "可支配所得": "845388"
    }
  ],
  "2003年": [
    {
      "地區": "臺灣地區",
      "可支配所得": "881662"
    },
    {
      "地區": "新北市",
      "可支配所得": "905166"
    },
    {
      "地區": "臺北市",
      "可支配所得": "1232396"
    },
    {
      "地區": "桃園市",
      "可支配所得": "959744"
    },
    {
      "地區": "臺中市",
      "可支配所得": "856510"
    },
    {
      "地區": "臺南市",
      "可支配所得": "786875"
    },
    {
      "地區": "高雄市",
      "可支配所得": "802658"
    },
    {
      "地區": "宜蘭縣",
      "可支配所得": "779157"
    },
    {
      "地區": "新竹縣",
      "可支配所得": "930761"
    },
    {
      "地區": "苗栗縣",
      "可支配所得": "778215"
    },
    {
      "地區": "彰化縣",
      "可支配所得": "816066"
    },
    {
      "地區": "南投縣",
      "可支配所得": "681544"
    },
    {
      "地區": "雲林縣",
      "可支配所得": "673606"
    },
    {
      "地區": "嘉義縣",
      "可支配所得": "615943"
    },
    {
      "地區": "屏東縣",
      "可支配所得": "757714"
    },
    {
      "地區": "臺東縣",
      "可支配所得": "619787"
    },
    {
      "地區": "花蓮縣",
      "可支配所得": "730767"
    },
    {
      "地區": "澎湖縣",
      "可支配所得": "588048"
    },
    {
      "地區": "基隆市",
      "可支配所得": "726013"
    },
    {
      "地區": "新竹市",
      "可支配所得": "1078255"
    },
    {
      "地區": "嘉義市",
      "可支配所得": "772203"
    }
  ],
  "2004年": [
    {
      "地區": "臺灣地區",
      "可支配所得": "891249"
    },
    {
      "地區": "新北市",
      "可支配所得": "918055"
    },
    {
      "地區": "臺北市",
      "可支配所得": "1225096"
    },
    {
      "地區": "桃園市",
      "可支配所得": "995951"
    },
    {
      "地區": "臺中市",
      "可支配所得": "820520"
    },
    {
      "地區": "臺南市",
      "可支配所得": "787897"
    },
    {
      "地區": "高雄市",
      "可支配所得": "841900"
    },
    {
      "地區": "宜蘭縣",
      "可支配所得": "729324"
    },
    {
      "地區": "新竹縣",
      "可支配所得": "975383"
    },
    {
      "地區": "苗栗縣",
      "可支配所得": "732410"
    },
    {
      "地區": "彰化縣",
      "可支配所得": "803292"
    },
    {
      "地區": "南投縣",
      "可支配所得": "738359"
    },
    {
      "地區": "雲林縣",
      "可支配所得": "703806"
    },
    {
      "地區": "嘉義縣",
      "可支配所得": "661697"
    },
    {
      "地區": "屏東縣",
      "可支配所得": "703809"
    },
    {
      "地區": "臺東縣",
      "可支配所得": "631719"
    },
    {
      "地區": "花蓮縣",
      "可支配所得": "714810"
    },
    {
      "地區": "澎湖縣",
      "可支配所得": "720582"
    },
    {
      "地區": "基隆市",
      "可支配所得": "868343"
    },
    {
      "地區": "新竹市",
      "可支配所得": "1217297"
    },
    {
      "地區": "嘉義市",
      "可支配所得": "694118"
    }
  ],
  "2005年": [
    {
      "地區": "臺灣地區",
      "可支配所得": "894574"
    },
    {
      "地區": "新北市",
      "可支配所得": "934211"
    },
    {
      "地區": "臺北市",
      "可支配所得": "1236014"
    },
    {
      "地區": "桃園市",
      "可支配所得": "985537"
    },
    {
      "地區": "臺中市",
      "可支配所得": "829541"
    },
    {
      "地區": "臺南市",
      "可支配所得": "737099"
    },
    {
      "地區": "高雄市",
      "可支配所得": "863104"
    },
    {
      "地區": "宜蘭縣",
      "可支配所得": "822477"
    },
    {
      "地區": "新竹縣",
      "可支配所得": "1053182"
    },
    {
      "地區": "苗栗縣",
      "可支配所得": "768863"
    },
    {
      "地區": "彰化縣",
      "可支配所得": "765433"
    },
    {
      "地區": "南投縣",
      "可支配所得": "748483"
    },
    {
      "地區": "雲林縣",
      "可支配所得": "648685"
    },
    {
      "地區": "嘉義縣",
      "可支配所得": "679081"
    },
    {
      "地區": "屏東縣",
      "可支配所得": "741094"
    },
    {
      "地區": "臺東縣",
      "可支配所得": "597433"
    },
    {
      "地區": "花蓮縣",
      "可支配所得": "662744"
    },
    {
      "地區": "澎湖縣",
      "可支配所得": "628399"
    },
    {
      "地區": "基隆市",
      "可支配所得": "875160"
    },
    {
      "地區": "新竹市",
      "可支配所得": "1092427"
    },
    {
      "地區": "嘉義市",
      "可支配所得": "812886"
    }
  ],
  "2006年": [
    {
      "地區": "臺灣地區",
      "可支配所得": "913092"
    },
    {
      "地區": "新北市",
      "可支配所得": "930130"
    },
    {
      "地區": "臺北市",
      "可支配所得": "1262406"
    },
    {
      "地區": "桃園市",
      "可支配所得": "981273"
    },
    {
      "地區": "臺中市",
      "可支配所得": "881886"
    },
    {
      "地區": "臺南市",
      "可支配所得": "791254"
    },
    {
      "地區": "高雄市",
      "可支配所得": "848785"
    },
    {
      "地區": "宜蘭縣",
      "可支配所得": "767861"
    },
    {
      "地區": "新竹縣",
      "可支配所得": "957811"
    },
    {
      "地區": "苗栗縣",
      "可支配所得": "849510"
    },
    {
      "地區": "彰化縣",
      "可支配所得": "815377"
    },
    {
      "地區": "南投縣",
      "可支配所得": "815573"
    },
    {
      "地區": "雲林縣",
      "可支配所得": "764109"
    },
    {
      "地區": "嘉義縣",
      "可支配所得": "697288"
    },
    {
      "地區": "屏東縣",
      "可支配所得": "747713"
    },
    {
      "地區": "臺東縣",
      "可支配所得": "624932"
    },
    {
      "地區": "花蓮縣",
      "可支配所得": "726258"
    },
    {
      "地區": "澎湖縣",
      "可支配所得": "705881"
    },
    {
      "地區": "基隆市",
      "可支配所得": "782453"
    },
    {
      "地區": "新竹市",
      "可支配所得": "1171277"
    },
    {
      "地區": "嘉義市",
      "可支配所得": "800693"
    }
  ],
  "2007年": [
    {
      "地區": "臺灣地區",
      "可支配所得": "923874"
    },
    {
      "地區": "新北市",
      "可支配所得": "912968"
    },
    {
      "地區": "臺北市",
      "可支配所得": "1287803"
    },
    {
      "地區": "桃園市",
      "可支配所得": "1003789"
    },
    {
      "地區": "臺中市",
      "可支配所得": "930676"
    },
    {
      "地區": "臺南市",
      "可支配所得": "815882"
    },
    {
      "地區": "高雄市",
      "可支配所得": "900028"
    },
    {
      "地區": "宜蘭縣",
      "可支配所得": "750870"
    },
    {
      "地區": "新竹縣",
      "可支配所得": "910180"
    },
    {
      "地區": "苗栗縣",
      "可支配所得": "826541"
    },
    {
      "地區": "彰化縣",
      "可支配所得": "776371"
    },
    {
      "地區": "南投縣",
      "可支配所得": "722209"
    },
    {
      "地區": "雲林縣",
      "可支配所得": "663716"
    },
    {
      "地區": "嘉義縣",
      "可支配所得": "638887"
    },
    {
      "地區": "屏東縣",
      "可支配所得": "796114"
    },
    {
      "地區": "臺東縣",
      "可支配所得": "720459"
    },
    {
      "地區": "花蓮縣",
      "可支配所得": "724680"
    },
    {
      "地區": "澎湖縣",
      "可支配所得": "644462"
    },
    {
      "地區": "基隆市",
      "可支配所得": "851508"
    },
    {
      "地區": "新竹市",
      "可支配所得": "1277464"
    },
    {
      "地區": "嘉義市",
      "可支配所得": "730039"
    }
  ],
  "2008年": [
    {
      "地區": "臺灣地區",
      "可支配所得": "913687"
    },
    {
      "地區": "新北市",
      "可支配所得": "972062"
    },
    {
      "地區": "臺北市",
      "可支配所得": "1271060"
    },
    {
      "地區": "桃園市",
      "可支配所得": "960037"
    },
    {
      "地區": "臺中市",
      "可支配所得": "861977"
    },
    {
      "地區": "臺南市",
      "可支配所得": "810038"
    },
    {
      "地區": "高雄市",
      "可支配所得": "884720"
    },
    {
      "地區": "宜蘭縣",
      "可支配所得": "847932"
    },
    {
      "地區": "新竹縣",
      "可支配所得": "1063948"
    },
    {
      "地區": "苗栗縣",
      "可支配所得": "754346"
    },
    {
      "地區": "彰化縣",
      "可支配所得": "760545"
    },
    {
      "地區": "南投縣",
      "可支配所得": "708936"
    },
    {
      "地區": "雲林縣",
      "可支配所得": "643980"
    },
    {
      "地區": "嘉義縣",
      "可支配所得": "655130"
    },
    {
      "地區": "屏東縣",
      "可支配所得": "701111"
    },
    {
      "地區": "臺東縣",
      "可支配所得": "586479"
    },
    {
      "地區": "花蓮縣",
      "可支配所得": "695030"
    },
    {
      "地區": "澎湖縣",
      "可支配所得": "732450"
    },
    {
      "地區": "基隆市",
      "可支配所得": "816692"
    },
    {
      "地區": "新竹市",
      "可支配所得": "1187288"
    },
    {
      "地區": "嘉義市",
      "可支配所得": "741393"
    }
  ],
  "2009年": [
    {
      "地區": "臺灣地區",
      "可支配所得": "887605"
    },
    {
      "地區": "新北市",
      "可支配所得": "922690"
    },
    {
      "地區": "臺北市",
      "可支配所得": "1246310"
    },
    {
      "地區": "桃園市",
      "可支配所得": "940942"
    },
    {
      "地區": "臺中市",
      "可支配所得": "814673"
    },
    {
      "地區": "臺南市",
      "可支配所得": "770804"
    },
    {
      "地區": "高雄市",
      "可支配所得": "869558"
    },
    {
      "地區": "宜蘭縣",
      "可支配所得": "746261"
    },
    {
      "地區": "新竹縣",
      "可支配所得": "1011033"
    },
    {
      "地區": "苗栗縣",
      "可支配所得": "756823"
    },
    {
      "地區": "彰化縣",
      "可支配所得": "750697"
    },
    {
      "地區": "南投縣",
      "可支配所得": "808713"
    },
    {
      "地區": "雲林縣",
      "可支配所得": "615006"
    },
    {
      "地區": "嘉義縣",
      "可支配所得": "629952"
    },
    {
      "地區": "屏東縣",
      "可支配所得": "727434"
    },
    {
      "地區": "臺東縣",
      "可支配所得": "667547"
    },
    {
      "地區": "花蓮縣",
      "可支配所得": "655696"
    },
    {
      "地區": "澎湖縣",
      "可支配所得": "689166"
    },
    {
      "地區": "基隆市",
      "可支配所得": "863161"
    },
    {
      "地區": "新竹市",
      "可支配所得": "1133833"
    },
    {
      "地區": "嘉義市",
      "可支配所得": "686637"
    }
  ],
  "2010年": [
    {
      "地區": "臺灣地區",
      "可支配所得": "889353"
    },
    {
      "地區": "新北市",
      "可支配所得": "893859"
    },
    {
      "地區": "臺北市",
      "可支配所得": "1298640"
    },
    {
      "地區": "桃園市",
      "可支配所得": "915499"
    },
    {
      "地區": "臺中市",
      "可支配所得": "823848"
    },
    {
      "地區": "臺南市",
      "可支配所得": "740706"
    },
    {
      "地區": "高雄市",
      "可支配所得": "873346"
    },
    {
      "地區": "宜蘭縣",
      "可支配所得": "802483"
    },
    {
      "地區": "新竹縣",
      "可支配所得": "1052587"
    },
    {
      "地區": "苗栗縣",
      "可支配所得": "788968"
    },
    {
      "地區": "彰化縣",
      "可支配所得": "741050"
    },
    {
      "地區": "南投縣",
      "可支配所得": "782905"
    },
    {
      "地區": "雲林縣",
      "可支配所得": "616480"
    },
    {
      "地區": "嘉義縣",
      "可支配所得": "658489"
    },
    {
      "地區": "屏東縣",
      "可支配所得": "704748"
    },
    {
      "地區": "臺東縣",
      "可支配所得": "568409"
    },
    {
      "地區": "花蓮縣",
      "可支配所得": "741246"
    },
    {
      "地區": "澎湖縣",
      "可支配所得": "827323"
    },
    {
      "地區": "基隆市",
      "可支配所得": "860445"
    },
    {
      "地區": "新竹市",
      "可支配所得": "1184598"
    },
    {
      "地區": "嘉義市",
      "可支配所得": "698454"
    }
  ],
  "2011年": [
    {
      "地區": "臺灣地區",
      "可支配所得": "907988"
    },
    {
      "地區": "新北市",
      "可支配所得": "927075"
    },
    {
      "地區": "臺北市",
      "可支配所得": "1251519"
    },
    {
      "地區": "桃園市",
      "可支配所得": "961998"
    },
    {
      "地區": "臺中市",
      "可支配所得": "915341"
    },
    {
      "地區": "臺南市",
      "可支配所得": "783223"
    },
    {
      "地區": "高雄市",
      "可支配所得": "856346"
    },
    {
      "地區": "宜蘭縣",
      "可支配所得": "721410"
    },
    {
      "地區": "新竹縣",
      "可支配所得": "1097918"
    },
    {
      "地區": "苗栗縣",
      "可支配所得": "833967"
    },
    {
      "地區": "彰化縣",
      "可支配所得": "772072"
    },
    {
      "地區": "南投縣",
      "可支配所得": "729037"
    },
    {
      "地區": "雲林縣",
      "可支配所得": "674055"
    },
    {
      "地區": "嘉義縣",
      "可支配所得": "687869"
    },
    {
      "地區": "屏東縣",
      "可支配所得": "710173"
    },
    {
      "地區": "臺東縣",
      "可支配所得": "607872"
    },
    {
      "地區": "花蓮縣",
      "可支配所得": "757041"
    },
    {
      "地區": "澎湖縣",
      "可支配所得": "673081"
    },
    {
      "地區": "基隆市",
      "可支配所得": "845677"
    },
    {
      "地區": "新竹市",
      "可支配所得": "1152707"
    },
    {
      "地區": "嘉義市",
      "可支配所得": "768315"
    }
  ],
  "2012年": [
    {
      "地區": "臺灣地區",
      "可支配所得": "923584"
    },
    {
      "地區": "新北市",
      "可支配所得": "911915"
    },
    {
      "地區": "臺北市",
      "可支配所得": "1278278"
    },
    {
      "地區": "桃園市",
      "可支配所得": "1007045"
    },
    {
      "地區": "臺中市",
      "可支配所得": "886682"
    },
    {
      "地區": "臺南市",
      "可支配所得": "770078"
    },
    {
      "地區": "高雄市",
      "可支配所得": "894107"
    },
    {
      "地區": "宜蘭縣",
      "可支配所得": "892727"
    },
    {
      "地區": "新竹縣",
      "可支配所得": "1093853"
    },
    {
      "地區": "苗栗縣",
      "可支配所得": "826530"
    },
    {
      "地區": "彰化縣",
      "可支配所得": "792362"
    },
    {
      "地區": "南投縣",
      "可支配所得": "831790"
    },
    {
      "地區": "雲林縣",
      "可支配所得": "684977"
    },
    {
      "地區": "嘉義縣",
      "可支配所得": "747956"
    },
    {
      "地區": "屏東縣",
      "可支配所得": "736174"
    },
    {
      "地區": "臺東縣",
      "可支配所得": "670017"
    },
    {
      "地區": "花蓮縣",
      "可支配所得": "761611"
    },
    {
      "地區": "澎湖縣",
      "可支配所得": "727056"
    },
    {
      "地區": "基隆市",
      "可支配所得": "786441"
    },
    {
      "地區": "新竹市",
      "可支配所得": "1132620"
    },
    {
      "地區": "嘉義市",
      "可支配所得": "910601"
    }
  ],
  "2013年": [
    {
      "地區": "臺灣地區",
      "可支配所得": "942208"
    },
    {
      "地區": "新北市",
      "可支配所得": "931239"
    },
    {
      "地區": "臺北市",
      "可支配所得": "1279195"
    },
    {
      "地區": "桃園市",
      "可支配所得": "1027658"
    },
    {
      "地區": "臺中市",
      "可支配所得": "928938"
    },
    {
      "地區": "臺南市",
      "可支配所得": "830467"
    },
    {
      "地區": "高雄市",
      "可支配所得": "915255"
    },
    {
      "地區": "宜蘭縣",
      "可支配所得": "813875"
    },
    {
      "地區": "新竹縣",
      "可支配所得": "1073893"
    },
    {
      "地區": "苗栗縣",
      "可支配所得": "839394"
    },
    {
      "地區": "彰化縣",
      "可支配所得": "789742"
    },
    {
      "地區": "南投縣",
      "可支配所得": "748930"
    },
    {
      "地區": "雲林縣",
      "可支配所得": "704313"
    },
    {
      "地區": "嘉義縣",
      "可支配所得": "727426"
    },
    {
      "地區": "屏東縣",
      "可支配所得": "722101"
    },
    {
      "地區": "臺東縣",
      "可支配所得": "676390"
    },
    {
      "地區": "花蓮縣",
      "可支配所得": "790373"
    },
    {
      "地區": "澎湖縣",
      "可支配所得": "769955"
    },
    {
      "地區": "基隆市",
      "可支配所得": "841832"
    },
    {
      "地區": "新竹市",
      "可支配所得": "1224310"
    },
    {
      "地區": "嘉義市",
      "可支配所得": "1026305"
    }
  ],
  "2014年": [
    {
      "地區": "臺灣地區",
      "可支配所得": "956849"
    },
    {
      "地區": "新北市",
      "可支配所得": "947670"
    },
    {
      "地區": "臺北市",
      "可支配所得": "1292604"
    },
    {
      "地區": "桃園市",
      "可支配所得": "1088867"
    },
    {
      "地區": "臺中市",
      "可支配所得": "955599"
    },
    {
      "地區": "臺南市",
      "可支配所得": "829957"
    },
    {
      "地區": "高雄市",
      "可支配所得": "917659"
    },
    {
      "地區": "宜蘭縣",
      "可支配所得": "902604"
    },
    {
      "地區": "新竹縣",
      "可支配所得": "1108941"
    },
    {
      "地區": "苗栗縣",
      "可支配所得": "913472"
    },
    {
      "地區": "彰化縣",
      "可支配所得": "783460"
    },
    {
      "地區": "南投縣",
      "可支配所得": "782566"
    },
    {
      "地區": "雲林縣",
      "可支配所得": "730035"
    },
    {
      "地區": "嘉義縣",
      "可支配所得": "667933"
    },
    {
      "地區": "屏東縣",
      "可支配所得": "699548"
    },
    {
      "地區": "臺東縣",
      "可支配所得": "697540"
    },
    {
      "地區": "花蓮縣",
      "可支配所得": "715443"
    },
    {
      "地區": "澎湖縣",
      "可支配所得": "771376"
    },
    {
      "地區": "基隆市",
      "可支配所得": "804007"
    },
    {
      "地區": "新竹市",
      "可支配所得": "1245600"
    },
    {
      "地區": "嘉義市",
      "可支配所得": "958377"
    }
  ],
  "2015年": [
    {
      "地區": "臺灣地區",
      "可支配所得": "964895"
    },
    {
      "地區": "新北市",
      "可支配所得": "959507"
    },
    {
      "地區": "臺北市",
      "可支配所得": "1314031"
    },
    {
      "地區": "桃園市",
      "可支配所得": "1073806"
    },
    {
      "地區": "臺中市",
      "可支配所得": "970157"
    },
    {
      "地區": "臺南市",
      "可支配所得": "837530"
    },
    {
      "地區": "高雄市",
      "可支配所得": "946918"
    },
    {
      "地區": "宜蘭縣",
      "可支配所得": "961095"
    },
    {
      "地區": "新竹縣",
      "可支配所得": "1026352"
    },
    {
      "地區": "苗栗縣",
      "可支配所得": "827540"
    },
    {
      "地區": "彰化縣",
      "可支配所得": "775465"
    },
    {
      "地區": "南投縣",
      "可支配所得": "738754"
    },
    {
      "地區": "雲林縣",
      "可支配所得": "732732"
    },
    {
      "地區": "嘉義縣",
      "可支配所得": "751058"
    },
    {
      "地區": "屏東縣",
      "可支配所得": "735650"
    },
    {
      "地區": "臺東縣",
      "可支配所得": "636162"
    },
    {
      "地區": "花蓮縣",
      "可支配所得": "768611"
    },
    {
      "地區": "澎湖縣",
      "可支配所得": "673239"
    },
    {
      "地區": "基隆市",
      "可支配所得": "896581"
    },
    {
      "地區": "新竹市",
      "可支配所得": "1136385"
    },
    {
      "地區": "嘉義市",
      "可支配所得": "917788"
    }
  ]
}